[{"_id":"fa24ce1a61796c0202b5d804400ec91d","bannerImageUrl":"https://636c-cloud1-4g2sqww73b1fdf3f-1306568592.tcb.qcloud.la/cloudbase-cms/upload/2021-10-27/463qd506ot4v0xpkvm7q6ia6u3xv7xg1_.jpg?sign=5fd1abf192cf836e8457a807563e2abf&t=1635347455","created_time":1635347458179,"updated_time":1637248582886,"description":"<p style=\"text-indent:2em;\"><span style=\"letter-spacing:0px\"><span style=\"line-height:1.5\"><span style=\"font-size:14px\">中国制造的Model3标准续航升级版将进一步拉低Model 3的起售价格，同时保持了Tesla一以贯之的高性能与高科技配置。</span></span></span></p><p style=\"text-indent:2em;\"><span style=\"letter-spacing:0px\"><span style=\"line-height:1.5\"><span style=\"font-size:14px\">中国制造的Model3标准续航升级版将进一步拉低Model 3的起售价格，同时保持了Tesla一以贯之的高性能与高科技配置。</span></span></span></p><p style=\"text-indent:2em;\"><span style=\"letter-spacing:0px\"><span style=\"line-height:1.5\"><span style=\"font-size:14px\">中国制造的Model3标准续航升级版将进一步拉低Model 3的起售价格，同时保持了Tesla一以贯之的高性能与高科技配置。</span></span></span></p>","productLine":[{"configList":[{"label":"起售价格","value":"235,900"},{"label":"起售价格","value":"235,900"},{"label":"起售价格","value":"235,900"}],"price":"340000","subtitle":"标准续航版","title":"Model 3"},{"configList":[{"label":"起售价格","value":"235,900"},{"label":"起售价格","value":"235,900"},{"label":"起售价格","value":"235,900"},null],"price":"270000","subtitle":"标准续航版","title":"Model 3"},{"configList":[{"label":"起售价格","value":"235,900"},{"label":"起售价格","value":"235,900"},{"label":"起售价格","value":"235,900"}],"price":"370000","subtitle":"标准续航版","title":"Model 3"}],"carPic":"https://636c-cloud1-4g2sqww73b1fdf3f-1306568592.tcb.qcloud.la/cloudbase-cms/upload/2021-11-18/ap7zfkrk7zozcqa7zr1yycudan5585p6_.jpg?sign=6901ac7dbb9ccd77a148880f1eb3d860&t=1637248580","name":"Model 3"},{"_id":"18ed0968617ab49b025686c32c531af1","bannerImageUrl":"https://636c-cloud1-4g2sqww73b1fdf3f-1306568592.tcb.qcloud.la/cloudbase-cms/upload/2021-10-28/n60g595pnm6nj1jduqqzov4hvrn8yulk_.jpg?sign=f820b1ca4bebff1d3a1f73836f0645d8&t=1635431559","carPic":"https://636c-cloud1-4g2sqww73b1fdf3f-1306568592.tcb.qcloud.la/cloudbase-cms/upload/2021-10-28/qqcppi1k74qpwbyth5h2r1xqnilngahz_.jpg?sign=f4d64f5b9c8b1e8379cc27bf662cc4f0&t=1635431576","description":"<p>大师傅大师傅似的</p>","name":"Model Y","productLine":[{"configList":[{"label":"起售价格","value":"235,900"},{"label":"起售价格","value":"235,900"},{"label":"起售价格","value":"235,900"}],"price":"370000","subtitle":"标准续航版","title":"标准续航版"},{"configList":[{"label":"起售价格","value":"235,900"},{"label":"起售价格","value":"235,900"},{"label":"起售价格","value":"235,900"}],"price":"370000","subtitle":"标准续航版","title":"标准续航版"},{"configList":[{"label":"起售价格","value":"235,900"},{"label":"起售价格","value":"235,900"},{"label":"起售价格","value":"235,900"}],"price":"370000","subtitle":"标准续航版","title":"Model 3"}],"created_time":1635431579057,"updated_time":1637248110137}]